{
  "fund_code": "012637",
  "fund_name": "国泰中证全指软件ETF联接C",
  "holdings_asof_date": "2026-03-31",
  "stock_total_weight": 99.63,
  "parsed_weight": 60.8,
  "missing_weight": 38.83,
  "positions": [
    {
      "stock_code": "002230",
      "stock_name": "科大讯飞",
      "weight": 12.2
    },
    {
      "stock_code": "300033",
      "stock_name": "同花顺",
      "weight": 7.33
    },
    {
      "stock_code": "688111",
      "stock_name": "金山办公",
      "weight": 6.18
    },
    {
      "stock_code": "002261",
      "stock_name": "拓维信息",
      "weight": 4.91
    },
    {
      "stock_code": "600570",
      "stock_name": "恒生电子",
      "weight": 4.42
    },
    {
      "stock_code": "601360",
      "stock_name": "三六零",
      "weight": 4.26
    },
    {
      "stock_code": "300803",
      "stock_name": "指南针",
      "weight": 3.98
    },
    {
      "stock_code": "300339",
      "stock_name": "润和软件",
      "weight": 3.51
    },
    {
      "stock_code": "300454",
      "stock_name": "深信服",
      "weight": 2.93
    },
    {
      "stock_code": "688568",
      "stock_name": "中科星图",
      "weight": 2.83
    },
    {
      "stock_code": "600536",
      "stock_name": "中国软件",
      "weight": 2.31
    },
    {
      "stock_code": "300166",
      "stock_name": "东方国信",
      "weight": 1.45
    },
    {
      "stock_code": "300229",
      "stock_name": "拓尔思",
      "weight": 1.41
    },
    {
      "stock_code": "300348",
      "stock_name": "长亮科技",
      "weight": 1.17
    },
    {
      "stock_code": "002063",
      "stock_name": "远光软件",
      "weight": 1.12
    },
    {
      "stock_code": "300188",
      "stock_name": "国投智能",
      "weight": 0.72
    },
    {
      "stock_code": "688795",
      "stock_name": "摩尔线程",
      "weight": 0.02
    },
    {
      "stock_code": "688765",
      "stock_name": "禾元生物",
      "weight": 0.02
    },
    {
      "stock_code": "688783",
      "stock_name": "西安奕材",
      "weight": 0.02
    },
    {
      "stock_code": "688802",
      "stock_name": "沐曦股份",
      "weight": 0.01
    }
  ],
  "fetched_at": "2026-04-27 13:55:42",
  "data_source": "eastmoney",
  "original_fund_code": "012637",
  "etf_target": "515230",
  "is_etf_link": true
}